<?xml version="1.0" encoding="UTF-8"?>
<?xml-stylesheet href="CoreNLP-to-HTML.xsl" type="text/xsl"?>
<root>
  <document>
    <sentences>
      <sentence id="1">
        <tokens>
          <token id="1">
            <word>alaska</word>
            <lemma>alaska</lemma>
            <CharacterOffsetBegin>0</CharacterOffsetBegin>
            <CharacterOffsetEnd>6</CharacterOffsetEnd>
            <POS>FW</POS>
            <NER>O</NER>
            <Speaker>PER0</Speaker>
          </token>
          <token id="2">
            <word>gov.</word>
            <lemma>gov.</lemma>
            <CharacterOffsetBegin>7</CharacterOffsetBegin>
            <CharacterOffsetEnd>11</CharacterOffsetEnd>
            <POS>FW</POS>
            <NER>O</NER>
            <Speaker>PER0</Speaker>
          </token>
          <token id="3">
            <word>sarah</word>
            <lemma>sarah</lemma>
            <CharacterOffsetBegin>12</CharacterOffsetBegin>
            <CharacterOffsetEnd>17</CharacterOffsetEnd>
            <POS>FW</POS>
            <NER>O</NER>
            <Speaker>PER0</Speaker>
          </token>
          <token id="4">
            <word>palin</word>
            <lemma>palin</lemma>
            <CharacterOffsetBegin>18</CharacterOffsetBegin>
            <CharacterOffsetEnd>23</CharacterOffsetEnd>
            <POS>NN</POS>
            <NER>O</NER>
            <Speaker>PER0</Speaker>
          </token>
          <token id="5">
            <word>'s</word>
            <lemma>'s</lemma>
            <CharacterOffsetBegin>24</CharacterOffsetBegin>
            <CharacterOffsetEnd>26</CharacterOffsetEnd>
            <POS>POS</POS>
            <NER>O</NER>
            <Speaker>PER0</Speaker>
          </token>
          <token id="6">
            <word>home</word>
            <lemma>home</lemma>
            <CharacterOffsetBegin>27</CharacterOffsetBegin>
            <CharacterOffsetEnd>31</CharacterOffsetEnd>
            <POS>NN</POS>
            <NER>O</NER>
            <Speaker>PER0</Speaker>
          </token>
          <token id="7">
            <word>church</word>
            <lemma>church</lemma>
            <CharacterOffsetBegin>32</CharacterOffsetBegin>
            <CharacterOffsetEnd>38</CharacterOffsetEnd>
            <POS>NN</POS>
            <NER>O</NER>
            <Speaker>PER0</Speaker>
          </token>
          <token id="8">
            <word>has</word>
            <lemma>have</lemma>
            <CharacterOffsetBegin>39</CharacterOffsetBegin>
            <CharacterOffsetEnd>42</CharacterOffsetEnd>
            <POS>VBZ</POS>
            <NER>O</NER>
            <Speaker>PER0</Speaker>
          </token>
          <token id="9">
            <word>been</word>
            <lemma>be</lemma>
            <CharacterOffsetBegin>43</CharacterOffsetBegin>
            <CharacterOffsetEnd>47</CharacterOffsetEnd>
            <POS>VBN</POS>
            <NER>O</NER>
            <Speaker>PER0</Speaker>
          </token>
          <token id="10">
            <word>badly</word>
            <lemma>badly</lemma>
            <CharacterOffsetBegin>48</CharacterOffsetBegin>
            <CharacterOffsetEnd>53</CharacterOffsetEnd>
            <POS>RB</POS>
            <NER>O</NER>
            <Speaker>PER0</Speaker>
          </token>
          <token id="11">
            <word>damaged</word>
            <lemma>damage</lemma>
            <CharacterOffsetBegin>54</CharacterOffsetBegin>
            <CharacterOffsetEnd>61</CharacterOffsetEnd>
            <POS>VBN</POS>
            <NER>O</NER>
            <Speaker>PER0</Speaker>
          </token>
          <token id="12">
            <word>in</word>
            <lemma>in</lemma>
            <CharacterOffsetBegin>62</CharacterOffsetBegin>
            <CharacterOffsetEnd>64</CharacterOffsetEnd>
            <POS>IN</POS>
            <NER>O</NER>
            <Speaker>PER0</Speaker>
          </token>
          <token id="13">
            <word>an</word>
            <lemma>a</lemma>
            <CharacterOffsetBegin>65</CharacterOffsetBegin>
            <CharacterOffsetEnd>67</CharacterOffsetEnd>
            <POS>DT</POS>
            <NER>O</NER>
            <Speaker>PER0</Speaker>
          </token>
          <token id="14">
            <word>arson</word>
            <lemma>arson</lemma>
            <CharacterOffsetBegin>68</CharacterOffsetBegin>
            <CharacterOffsetEnd>73</CharacterOffsetEnd>
            <POS>NN</POS>
            <NER>O</NER>
            <Speaker>PER0</Speaker>
          </token>
          <token id="15">
            <word>fire</word>
            <lemma>fire</lemma>
            <CharacterOffsetBegin>74</CharacterOffsetBegin>
            <CharacterOffsetEnd>78</CharacterOffsetEnd>
            <POS>NN</POS>
            <NER>O</NER>
            <Speaker>PER0</Speaker>
          </token>
          <token id="16">
            <word>.</word>
            <lemma>.</lemma>
            <CharacterOffsetBegin>79</CharacterOffsetBegin>
            <CharacterOffsetEnd>80</CharacterOffsetEnd>
            <POS>.</POS>
            <NER>O</NER>
            <Speaker>PER0</Speaker>
          </token>
        </tokens>
        <parse>(ROOT (NP (NP (FW alaska) (FW gov.) (FW sarah)) (SBAR (S (NP (NP (NN palin) (POS 's)) (NN home) (NN church)) (VP (VBZ has) (VP (VBN been) (VP (ADVP (RB badly)) (VBN damaged) (PP (IN in) (NP (DT an) (NN arson) (NN fire)))))))) (. .))) </parse>
        <dependencies type="basic-dependencies">
          <dep type="root">
            <governor idx="0">ROOT</governor>
            <dependent idx="3">sarah</dependent>
          </dep>
          <dep type="compound">
            <governor idx="3">sarah</governor>
            <dependent idx="1">alaska</dependent>
          </dep>
          <dep type="compound">
            <governor idx="3">sarah</governor>
            <dependent idx="2">gov.</dependent>
          </dep>
          <dep type="nmod:poss">
            <governor idx="7">church</governor>
            <dependent idx="4">palin</dependent>
          </dep>
          <dep type="case">
            <governor idx="4">palin</governor>
            <dependent idx="5">'s</dependent>
          </dep>
          <dep type="compound">
            <governor idx="7">church</governor>
            <dependent idx="6">home</dependent>
          </dep>
          <dep type="nsubjpass">
            <governor idx="11">damaged</governor>
            <dependent idx="7">church</dependent>
          </dep>
          <dep type="aux">
            <governor idx="11">damaged</governor>
            <dependent idx="8">has</dependent>
          </dep>
          <dep type="auxpass">
            <governor idx="11">damaged</governor>
            <dependent idx="9">been</dependent>
          </dep>
          <dep type="advmod">
            <governor idx="11">damaged</governor>
            <dependent idx="10">badly</dependent>
          </dep>
          <dep type="acl:relcl">
            <governor idx="3">sarah</governor>
            <dependent idx="11">damaged</dependent>
          </dep>
          <dep type="case">
            <governor idx="15">fire</governor>
            <dependent idx="12">in</dependent>
          </dep>
          <dep type="det">
            <governor idx="15">fire</governor>
            <dependent idx="13">an</dependent>
          </dep>
          <dep type="compound">
            <governor idx="15">fire</governor>
            <dependent idx="14">arson</dependent>
          </dep>
          <dep type="nmod">
            <governor idx="11">damaged</governor>
            <dependent idx="15">fire</dependent>
          </dep>
          <dep type="punct">
            <governor idx="3">sarah</governor>
            <dependent idx="16">.</dependent>
          </dep>
        </dependencies>
        <dependencies type="collapsed-dependencies">
          <dep type="root">
            <governor idx="0">ROOT</governor>
            <dependent idx="3">sarah</dependent>
          </dep>
          <dep type="compound">
            <governor idx="3">sarah</governor>
            <dependent idx="1">alaska</dependent>
          </dep>
          <dep type="compound">
            <governor idx="3">sarah</governor>
            <dependent idx="2">gov.</dependent>
          </dep>
          <dep type="nmod:poss">
            <governor idx="7">church</governor>
            <dependent idx="4">palin</dependent>
          </dep>
          <dep type="case">
            <governor idx="4">palin</governor>
            <dependent idx="5">'s</dependent>
          </dep>
          <dep type="compound">
            <governor idx="7">church</governor>
            <dependent idx="6">home</dependent>
          </dep>
          <dep type="nsubjpass">
            <governor idx="11">damaged</governor>
            <dependent idx="7">church</dependent>
          </dep>
          <dep type="aux">
            <governor idx="11">damaged</governor>
            <dependent idx="8">has</dependent>
          </dep>
          <dep type="auxpass">
            <governor idx="11">damaged</governor>
            <dependent idx="9">been</dependent>
          </dep>
          <dep type="advmod">
            <governor idx="11">damaged</governor>
            <dependent idx="10">badly</dependent>
          </dep>
          <dep type="acl:relcl">
            <governor idx="3">sarah</governor>
            <dependent idx="11">damaged</dependent>
          </dep>
          <dep type="case">
            <governor idx="15">fire</governor>
            <dependent idx="12">in</dependent>
          </dep>
          <dep type="det">
            <governor idx="15">fire</governor>
            <dependent idx="13">an</dependent>
          </dep>
          <dep type="compound">
            <governor idx="15">fire</governor>
            <dependent idx="14">arson</dependent>
          </dep>
          <dep type="nmod:in">
            <governor idx="11">damaged</governor>
            <dependent idx="15">fire</dependent>
          </dep>
          <dep type="punct">
            <governor idx="3">sarah</governor>
            <dependent idx="16">.</dependent>
          </dep>
        </dependencies>
        <dependencies type="collapsed-ccprocessed-dependencies">
          <dep type="root">
            <governor idx="0">ROOT</governor>
            <dependent idx="3">sarah</dependent>
          </dep>
          <dep type="compound">
            <governor idx="3">sarah</governor>
            <dependent idx="1">alaska</dependent>
          </dep>
          <dep type="compound">
            <governor idx="3">sarah</governor>
            <dependent idx="2">gov.</dependent>
          </dep>
          <dep type="nmod:poss">
            <governor idx="7">church</governor>
            <dependent idx="4">palin</dependent>
          </dep>
          <dep type="case">
            <governor idx="4">palin</governor>
            <dependent idx="5">'s</dependent>
          </dep>
          <dep type="compound">
            <governor idx="7">church</governor>
            <dependent idx="6">home</dependent>
          </dep>
          <dep type="nsubjpass">
            <governor idx="11">damaged</governor>
            <dependent idx="7">church</dependent>
          </dep>
          <dep type="aux">
            <governor idx="11">damaged</governor>
            <dependent idx="8">has</dependent>
          </dep>
          <dep type="auxpass">
            <governor idx="11">damaged</governor>
            <dependent idx="9">been</dependent>
          </dep>
          <dep type="advmod">
            <governor idx="11">damaged</governor>
            <dependent idx="10">badly</dependent>
          </dep>
          <dep type="acl:relcl">
            <governor idx="3">sarah</governor>
            <dependent idx="11">damaged</dependent>
          </dep>
          <dep type="case">
            <governor idx="15">fire</governor>
            <dependent idx="12">in</dependent>
          </dep>
          <dep type="det">
            <governor idx="15">fire</governor>
            <dependent idx="13">an</dependent>
          </dep>
          <dep type="compound">
            <governor idx="15">fire</governor>
            <dependent idx="14">arson</dependent>
          </dep>
          <dep type="nmod:in">
            <governor idx="11">damaged</governor>
            <dependent idx="15">fire</dependent>
          </dep>
          <dep type="punct">
            <governor idx="3">sarah</governor>
            <dependent idx="16">.</dependent>
          </dep>
        </dependencies>
        <dependencies type="enhanced-dependencies">
          <dep type="root">
            <governor idx="0">ROOT</governor>
            <dependent idx="3">sarah</dependent>
          </dep>
          <dep type="compound">
            <governor idx="3">sarah</governor>
            <dependent idx="1">alaska</dependent>
          </dep>
          <dep type="compound">
            <governor idx="3">sarah</governor>
            <dependent idx="2">gov.</dependent>
          </dep>
          <dep type="nmod:poss">
            <governor idx="7">church</governor>
            <dependent idx="4">palin</dependent>
          </dep>
          <dep type="case">
            <governor idx="4">palin</governor>
            <dependent idx="5">'s</dependent>
          </dep>
          <dep type="compound">
            <governor idx="7">church</governor>
            <dependent idx="6">home</dependent>
          </dep>
          <dep type="nsubjpass">
            <governor idx="11">damaged</governor>
            <dependent idx="7">church</dependent>
          </dep>
          <dep type="aux">
            <governor idx="11">damaged</governor>
            <dependent idx="8">has</dependent>
          </dep>
          <dep type="auxpass">
            <governor idx="11">damaged</governor>
            <dependent idx="9">been</dependent>
          </dep>
          <dep type="advmod">
            <governor idx="11">damaged</governor>
            <dependent idx="10">badly</dependent>
          </dep>
          <dep type="acl:relcl">
            <governor idx="3">sarah</governor>
            <dependent idx="11">damaged</dependent>
          </dep>
          <dep type="case">
            <governor idx="15">fire</governor>
            <dependent idx="12">in</dependent>
          </dep>
          <dep type="det">
            <governor idx="15">fire</governor>
            <dependent idx="13">an</dependent>
          </dep>
          <dep type="compound">
            <governor idx="15">fire</governor>
            <dependent idx="14">arson</dependent>
          </dep>
          <dep type="nmod:in">
            <governor idx="11">damaged</governor>
            <dependent idx="15">fire</dependent>
          </dep>
          <dep type="punct">
            <governor idx="3">sarah</governor>
            <dependent idx="16">.</dependent>
          </dep>
        </dependencies>
        <dependencies type="enhanced-plus-plus-dependencies">
          <dep type="root">
            <governor idx="0">ROOT</governor>
            <dependent idx="3">sarah</dependent>
          </dep>
          <dep type="compound">
            <governor idx="3">sarah</governor>
            <dependent idx="1">alaska</dependent>
          </dep>
          <dep type="compound">
            <governor idx="3">sarah</governor>
            <dependent idx="2">gov.</dependent>
          </dep>
          <dep type="nmod:poss">
            <governor idx="7">church</governor>
            <dependent idx="4">palin</dependent>
          </dep>
          <dep type="case">
            <governor idx="4">palin</governor>
            <dependent idx="5">'s</dependent>
          </dep>
          <dep type="compound">
            <governor idx="7">church</governor>
            <dependent idx="6">home</dependent>
          </dep>
          <dep type="nsubjpass">
            <governor idx="11">damaged</governor>
            <dependent idx="7">church</dependent>
          </dep>
          <dep type="aux">
            <governor idx="11">damaged</governor>
            <dependent idx="8">has</dependent>
          </dep>
          <dep type="auxpass">
            <governor idx="11">damaged</governor>
            <dependent idx="9">been</dependent>
          </dep>
          <dep type="advmod">
            <governor idx="11">damaged</governor>
            <dependent idx="10">badly</dependent>
          </dep>
          <dep type="acl:relcl">
            <governor idx="3">sarah</governor>
            <dependent idx="11">damaged</dependent>
          </dep>
          <dep type="case">
            <governor idx="15">fire</governor>
            <dependent idx="12">in</dependent>
          </dep>
          <dep type="det">
            <governor idx="15">fire</governor>
            <dependent idx="13">an</dependent>
          </dep>
          <dep type="compound">
            <governor idx="15">fire</governor>
            <dependent idx="14">arson</dependent>
          </dep>
          <dep type="nmod:in">
            <governor idx="11">damaged</governor>
            <dependent idx="15">fire</dependent>
          </dep>
          <dep type="punct">
            <governor idx="3">sarah</governor>
            <dependent idx="16">.</dependent>
          </dep>
        </dependencies>
      </sentence>
      <sentence id="2">
        <tokens>
          <token id="1">
            <word>damages</word>
            <lemma>damages</lemma>
            <CharacterOffsetBegin>81</CharacterOffsetBegin>
            <CharacterOffsetEnd>88</CharacterOffsetEnd>
            <POS>NNS</POS>
            <NER>O</NER>
            <Speaker>PER0</Speaker>
          </token>
          <token id="2">
            <word>to</word>
            <lemma>to</lemma>
            <CharacterOffsetBegin>89</CharacterOffsetBegin>
            <CharacterOffsetEnd>91</CharacterOffsetEnd>
            <POS>TO</POS>
            <NER>O</NER>
            <Speaker>PER0</Speaker>
          </token>
          <token id="3">
            <word>the</word>
            <lemma>the</lemma>
            <CharacterOffsetBegin>92</CharacterOffsetBegin>
            <CharacterOffsetEnd>95</CharacterOffsetEnd>
            <POS>DT</POS>
            <NER>O</NER>
            <Speaker>PER0</Speaker>
          </token>
          <token id="4">
            <word>wasilla</word>
            <lemma>wasilla</lemma>
            <CharacterOffsetBegin>96</CharacterOffsetBegin>
            <CharacterOffsetEnd>103</CharacterOffsetEnd>
            <POS>NN</POS>
            <NER>O</NER>
            <Speaker>PER0</Speaker>
          </token>
          <token id="5">
            <word>bible</word>
            <lemma>bible</lemma>
            <CharacterOffsetBegin>104</CharacterOffsetBegin>
            <CharacterOffsetEnd>109</CharacterOffsetEnd>
            <POS>JJ</POS>
            <NER>O</NER>
            <Speaker>PER0</Speaker>
          </token>
          <token id="6">
            <word>church</word>
            <lemma>church</lemma>
            <CharacterOffsetBegin>110</CharacterOffsetBegin>
            <CharacterOffsetEnd>116</CharacterOffsetEnd>
            <POS>NN</POS>
            <NER>O</NER>
            <Speaker>PER0</Speaker>
          </token>
          <token id="7">
            <word>are</word>
            <lemma>be</lemma>
            <CharacterOffsetBegin>117</CharacterOffsetBegin>
            <CharacterOffsetEnd>120</CharacterOffsetEnd>
            <POS>VBP</POS>
            <NER>O</NER>
            <Speaker>PER0</Speaker>
          </token>
          <token id="8">
            <word>estimated</word>
            <lemma>estimate</lemma>
            <CharacterOffsetBegin>121</CharacterOffsetBegin>
            <CharacterOffsetEnd>130</CharacterOffsetEnd>
            <POS>VBN</POS>
            <NER>O</NER>
            <Speaker>PER0</Speaker>
          </token>
          <token id="9">
            <word>at</word>
            <lemma>at</lemma>
            <CharacterOffsetBegin>131</CharacterOffsetBegin>
            <CharacterOffsetEnd>133</CharacterOffsetEnd>
            <POS>IN</POS>
            <NER>O</NER>
            <Speaker>PER0</Speaker>
          </token>
          <token id="10">
            <word>$</word>
            <lemma>$</lemma>
            <CharacterOffsetBegin>134</CharacterOffsetBegin>
            <CharacterOffsetEnd>135</CharacterOffsetEnd>
            <POS>$</POS>
            <NER>MONEY</NER>
            <NormalizedNER>$1000000.0</NormalizedNER>
            <Speaker>PER0</Speaker>
          </token>
          <token id="11">
            <word>1</word>
            <lemma>1</lemma>
            <CharacterOffsetBegin>136</CharacterOffsetBegin>
            <CharacterOffsetEnd>137</CharacterOffsetEnd>
            <POS>CD</POS>
            <NER>MONEY</NER>
            <NormalizedNER>$1000000.0</NormalizedNER>
            <Speaker>PER0</Speaker>
          </token>
          <token id="12">
            <word>million</word>
            <lemma>million</lemma>
            <CharacterOffsetBegin>138</CharacterOffsetBegin>
            <CharacterOffsetEnd>145</CharacterOffsetEnd>
            <POS>CD</POS>
            <NER>MONEY</NER>
            <NormalizedNER>$1000000.0</NormalizedNER>
            <Speaker>PER0</Speaker>
          </token>
          <token id="13">
            <word>.</word>
            <lemma>.</lemma>
            <CharacterOffsetBegin>146</CharacterOffsetBegin>
            <CharacterOffsetEnd>147</CharacterOffsetEnd>
            <POS>.</POS>
            <NER>O</NER>
            <Speaker>PER0</Speaker>
          </token>
        </tokens>
        <parse>(ROOT (S (NP (NP (NNS damages)) (PP (TO to) (NP (DT the) (NN wasilla) (JJ bible) (NN church)))) (VP (VBP are) (VP (VBN estimated) (PP (IN at) (NP (QP ($ $) (CD 1) (CD million)))))) (. .))) </parse>
        <dependencies type="basic-dependencies">
          <dep type="root">
            <governor idx="0">ROOT</governor>
            <dependent idx="8">estimated</dependent>
          </dep>
          <dep type="nsubjpass">
            <governor idx="8">estimated</governor>
            <dependent idx="1">damages</dependent>
          </dep>
          <dep type="case">
            <governor idx="6">church</governor>
            <dependent idx="2">to</dependent>
          </dep>
          <dep type="det">
            <governor idx="6">church</governor>
            <dependent idx="3">the</dependent>
          </dep>
          <dep type="compound">
            <governor idx="6">church</governor>
            <dependent idx="4">wasilla</dependent>
          </dep>
          <dep type="amod">
            <governor idx="6">church</governor>
            <dependent idx="5">bible</dependent>
          </dep>
          <dep type="nmod">
            <governor idx="1">damages</governor>
            <dependent idx="6">church</dependent>
          </dep>
          <dep type="auxpass">
            <governor idx="8">estimated</governor>
            <dependent idx="7">are</dependent>
          </dep>
          <dep type="case">
            <governor idx="10">$</governor>
            <dependent idx="9">at</dependent>
          </dep>
          <dep type="nmod">
            <governor idx="8">estimated</governor>
            <dependent idx="10">$</dependent>
          </dep>
          <dep type="compound">
            <governor idx="12">million</governor>
            <dependent idx="11">1</dependent>
          </dep>
          <dep type="nummod">
            <governor idx="10">$</governor>
            <dependent idx="12">million</dependent>
          </dep>
          <dep type="punct">
            <governor idx="8">estimated</governor>
            <dependent idx="13">.</dependent>
          </dep>
        </dependencies>
        <dependencies type="collapsed-dependencies">
          <dep type="root">
            <governor idx="0">ROOT</governor>
            <dependent idx="8">estimated</dependent>
          </dep>
          <dep type="nsubjpass">
            <governor idx="8">estimated</governor>
            <dependent idx="1">damages</dependent>
          </dep>
          <dep type="case">
            <governor idx="6">church</governor>
            <dependent idx="2">to</dependent>
          </dep>
          <dep type="det">
            <governor idx="6">church</governor>
            <dependent idx="3">the</dependent>
          </dep>
          <dep type="compound">
            <governor idx="6">church</governor>
            <dependent idx="4">wasilla</dependent>
          </dep>
          <dep type="amod">
            <governor idx="6">church</governor>
            <dependent idx="5">bible</dependent>
          </dep>
          <dep type="nmod:to">
            <governor idx="1">damages</governor>
            <dependent idx="6">church</dependent>
          </dep>
          <dep type="auxpass">
            <governor idx="8">estimated</governor>
            <dependent idx="7">are</dependent>
          </dep>
          <dep type="case">
            <governor idx="10">$</governor>
            <dependent idx="9">at</dependent>
          </dep>
          <dep type="nmod:at">
            <governor idx="8">estimated</governor>
            <dependent idx="10">$</dependent>
          </dep>
          <dep type="compound">
            <governor idx="12">million</governor>
            <dependent idx="11">1</dependent>
          </dep>
          <dep type="nummod">
            <governor idx="10">$</governor>
            <dependent idx="12">million</dependent>
          </dep>
          <dep type="punct">
            <governor idx="8">estimated</governor>
            <dependent idx="13">.</dependent>
          </dep>
        </dependencies>
        <dependencies type="collapsed-ccprocessed-dependencies">
          <dep type="root">
            <governor idx="0">ROOT</governor>
            <dependent idx="8">estimated</dependent>
          </dep>
          <dep type="nsubjpass">
            <governor idx="8">estimated</governor>
            <dependent idx="1">damages</dependent>
          </dep>
          <dep type="case">
            <governor idx="6">church</governor>
            <dependent idx="2">to</dependent>
          </dep>
          <dep type="det">
            <governor idx="6">church</governor>
            <dependent idx="3">the</dependent>
          </dep>
          <dep type="compound">
            <governor idx="6">church</governor>
            <dependent idx="4">wasilla</dependent>
          </dep>
          <dep type="amod">
            <governor idx="6">church</governor>
            <dependent idx="5">bible</dependent>
          </dep>
          <dep type="nmod:to">
            <governor idx="1">damages</governor>
            <dependent idx="6">church</dependent>
          </dep>
          <dep type="auxpass">
            <governor idx="8">estimated</governor>
            <dependent idx="7">are</dependent>
          </dep>
          <dep type="case">
            <governor idx="10">$</governor>
            <dependent idx="9">at</dependent>
          </dep>
          <dep type="nmod:at">
            <governor idx="8">estimated</governor>
            <dependent idx="10">$</dependent>
          </dep>
          <dep type="compound">
            <governor idx="12">million</governor>
            <dependent idx="11">1</dependent>
          </dep>
          <dep type="nummod">
            <governor idx="10">$</governor>
            <dependent idx="12">million</dependent>
          </dep>
          <dep type="punct">
            <governor idx="8">estimated</governor>
            <dependent idx="13">.</dependent>
          </dep>
        </dependencies>
        <dependencies type="enhanced-dependencies">
          <dep type="root">
            <governor idx="0">ROOT</governor>
            <dependent idx="8">estimated</dependent>
          </dep>
          <dep type="nsubjpass">
            <governor idx="8">estimated</governor>
            <dependent idx="1">damages</dependent>
          </dep>
          <dep type="case">
            <governor idx="6">church</governor>
            <dependent idx="2">to</dependent>
          </dep>
          <dep type="det">
            <governor idx="6">church</governor>
            <dependent idx="3">the</dependent>
          </dep>
          <dep type="compound">
            <governor idx="6">church</governor>
            <dependent idx="4">wasilla</dependent>
          </dep>
          <dep type="amod">
            <governor idx="6">church</governor>
            <dependent idx="5">bible</dependent>
          </dep>
          <dep type="nmod:to">
            <governor idx="1">damages</governor>
            <dependent idx="6">church</dependent>
          </dep>
          <dep type="auxpass">
            <governor idx="8">estimated</governor>
            <dependent idx="7">are</dependent>
          </dep>
          <dep type="case">
            <governor idx="10">$</governor>
            <dependent idx="9">at</dependent>
          </dep>
          <dep type="nmod:at">
            <governor idx="8">estimated</governor>
            <dependent idx="10">$</dependent>
          </dep>
          <dep type="compound">
            <governor idx="12">million</governor>
            <dependent idx="11">1</dependent>
          </dep>
          <dep type="nummod">
            <governor idx="10">$</governor>
            <dependent idx="12">million</dependent>
          </dep>
          <dep type="punct">
            <governor idx="8">estimated</governor>
            <dependent idx="13">.</dependent>
          </dep>
        </dependencies>
        <dependencies type="enhanced-plus-plus-dependencies">
          <dep type="root">
            <governor idx="0">ROOT</governor>
            <dependent idx="8">estimated</dependent>
          </dep>
          <dep type="nsubjpass">
            <governor idx="8">estimated</governor>
            <dependent idx="1">damages</dependent>
          </dep>
          <dep type="case">
            <governor idx="6">church</governor>
            <dependent idx="2">to</dependent>
          </dep>
          <dep type="det">
            <governor idx="6">church</governor>
            <dependent idx="3">the</dependent>
          </dep>
          <dep type="compound">
            <governor idx="6">church</governor>
            <dependent idx="4">wasilla</dependent>
          </dep>
          <dep type="amod">
            <governor idx="6">church</governor>
            <dependent idx="5">bible</dependent>
          </dep>
          <dep type="nmod:to">
            <governor idx="1">damages</governor>
            <dependent idx="6">church</dependent>
          </dep>
          <dep type="auxpass">
            <governor idx="8">estimated</governor>
            <dependent idx="7">are</dependent>
          </dep>
          <dep type="case">
            <governor idx="10">$</governor>
            <dependent idx="9">at</dependent>
          </dep>
          <dep type="nmod:at">
            <governor idx="8">estimated</governor>
            <dependent idx="10">$</dependent>
          </dep>
          <dep type="compound">
            <governor idx="12">million</governor>
            <dependent idx="11">1</dependent>
          </dep>
          <dep type="nummod">
            <governor idx="10">$</governor>
            <dependent idx="12">million</dependent>
          </dep>
          <dep type="punct">
            <governor idx="8">estimated</governor>
            <dependent idx="13">.</dependent>
          </dep>
        </dependencies>
      </sentence>
      <sentence id="3">
        <tokens>
          <token id="1">
            <word>the</word>
            <lemma>the</lemma>
            <CharacterOffsetBegin>148</CharacterOffsetBegin>
            <CharacterOffsetEnd>151</CharacterOffsetEnd>
            <POS>DT</POS>
            <NER>O</NER>
            <Speaker>PER0</Speaker>
          </token>
          <token id="2">
            <word>fire</word>
            <lemma>fire</lemma>
            <CharacterOffsetBegin>152</CharacterOffsetBegin>
            <CharacterOffsetEnd>156</CharacterOffsetEnd>
            <POS>NN</POS>
            <NER>O</NER>
            <Speaker>PER0</Speaker>
          </token>
          <token id="3">
            <word>chief</word>
            <lemma>chief</lemma>
            <CharacterOffsetBegin>157</CharacterOffsetBegin>
            <CharacterOffsetEnd>162</CharacterOffsetEnd>
            <POS>NN</POS>
            <NER>O</NER>
            <Speaker>PER0</Speaker>
          </token>
          <token id="4">
            <word>says</word>
            <lemma>say</lemma>
            <CharacterOffsetBegin>163</CharacterOffsetBegin>
            <CharacterOffsetEnd>167</CharacterOffsetEnd>
            <POS>VBZ</POS>
            <NER>O</NER>
            <Speaker>PER0</Speaker>
          </token>
          <token id="5">
            <word>the</word>
            <lemma>the</lemma>
            <CharacterOffsetBegin>168</CharacterOffsetBegin>
            <CharacterOffsetEnd>171</CharacterOffsetEnd>
            <POS>DT</POS>
            <NER>O</NER>
            <Speaker>PER0</Speaker>
          </token>
          <token id="6">
            <word>fire</word>
            <lemma>fire</lemma>
            <CharacterOffsetBegin>172</CharacterOffsetBegin>
            <CharacterOffsetEnd>176</CharacterOffsetEnd>
            <POS>NN</POS>
            <NER>O</NER>
            <Speaker>PER0</Speaker>
          </token>
          <token id="7">
            <word>''</word>
            <lemma>''</lemma>
            <CharacterOffsetBegin>177</CharacterOffsetBegin>
            <CharacterOffsetEnd>178</CharacterOffsetEnd>
            <POS>''</POS>
            <NER>O</NER>
            <Speaker>PER0</Speaker>
          </token>
          <token id="8">
            <word>is</word>
            <lemma>be</lemma>
            <CharacterOffsetBegin>179</CharacterOffsetBegin>
            <CharacterOffsetEnd>181</CharacterOffsetEnd>
            <POS>VBZ</POS>
            <NER>O</NER>
            <Speaker>PER0</Speaker>
          </token>
          <token id="9">
            <word>definitely</word>
            <lemma>definitely</lemma>
            <CharacterOffsetBegin>182</CharacterOffsetBegin>
            <CharacterOffsetEnd>192</CharacterOffsetEnd>
            <POS>RB</POS>
            <NER>O</NER>
            <Speaker>PER0</Speaker>
          </token>
          <token id="10">
            <word>suspicious</word>
            <lemma>suspicious</lemma>
            <CharacterOffsetBegin>193</CharacterOffsetBegin>
            <CharacterOffsetEnd>203</CharacterOffsetEnd>
            <POS>JJ</POS>
            <NER>O</NER>
            <Speaker>PER0</Speaker>
          </token>
          <token id="11">
            <word>.</word>
            <lemma>.</lemma>
            <CharacterOffsetBegin>204</CharacterOffsetBegin>
            <CharacterOffsetEnd>205</CharacterOffsetEnd>
            <POS>.</POS>
            <NER>O</NER>
            <Speaker>PER0</Speaker>
          </token>
          <token id="12">
            <word>''</word>
            <lemma>''</lemma>
            <CharacterOffsetBegin>206</CharacterOffsetBegin>
            <CharacterOffsetEnd>207</CharacterOffsetEnd>
            <POS>''</POS>
            <NER>O</NER>
            <Speaker>PER0</Speaker>
          </token>
        </tokens>
        <parse>(ROOT (S (NP (DT the) (NN fire) (NN chief)) (VP (VBZ says) (NP (NP (DT the) (NN fire)) ('' '') (SBAR (S (VP (VBZ is) (ADVP (RB definitely)) (ADJP (JJ suspicious))))))) (. .) ('' ''))) </parse>
        <dependencies type="basic-dependencies">
          <dep type="root">
            <governor idx="0">ROOT</governor>
            <dependent idx="4">says</dependent>
          </dep>
          <dep type="det">
            <governor idx="3">chief</governor>
            <dependent idx="1">the</dependent>
          </dep>
          <dep type="compound">
            <governor idx="3">chief</governor>
            <dependent idx="2">fire</dependent>
          </dep>
          <dep type="nsubj">
            <governor idx="4">says</governor>
            <dependent idx="3">chief</dependent>
          </dep>
          <dep type="det">
            <governor idx="6">fire</governor>
            <dependent idx="5">the</dependent>
          </dep>
          <dep type="dobj">
            <governor idx="4">says</governor>
            <dependent idx="6">fire</dependent>
          </dep>
          <dep type="punct">
            <governor idx="6">fire</governor>
            <dependent idx="7">''</dependent>
          </dep>
          <dep type="cop">
            <governor idx="10">suspicious</governor>
            <dependent idx="8">is</dependent>
          </dep>
          <dep type="advmod">
            <governor idx="10">suspicious</governor>
            <dependent idx="9">definitely</dependent>
          </dep>
          <dep type="acl:relcl">
            <governor idx="6">fire</governor>
            <dependent idx="10">suspicious</dependent>
          </dep>
          <dep type="punct">
            <governor idx="4">says</governor>
            <dependent idx="11">.</dependent>
          </dep>
          <dep type="punct">
            <governor idx="4">says</governor>
            <dependent idx="12">''</dependent>
          </dep>
        </dependencies>
        <dependencies type="collapsed-dependencies">
          <dep type="root">
            <governor idx="0">ROOT</governor>
            <dependent idx="4">says</dependent>
          </dep>
          <dep type="det">
            <governor idx="3">chief</governor>
            <dependent idx="1">the</dependent>
          </dep>
          <dep type="compound">
            <governor idx="3">chief</governor>
            <dependent idx="2">fire</dependent>
          </dep>
          <dep type="nsubj">
            <governor idx="4">says</governor>
            <dependent idx="3">chief</dependent>
          </dep>
          <dep type="det">
            <governor idx="6">fire</governor>
            <dependent idx="5">the</dependent>
          </dep>
          <dep type="dobj">
            <governor idx="4">says</governor>
            <dependent idx="6">fire</dependent>
          </dep>
          <dep type="punct">
            <governor idx="6">fire</governor>
            <dependent idx="7">''</dependent>
          </dep>
          <dep type="cop">
            <governor idx="10">suspicious</governor>
            <dependent idx="8">is</dependent>
          </dep>
          <dep type="advmod">
            <governor idx="10">suspicious</governor>
            <dependent idx="9">definitely</dependent>
          </dep>
          <dep type="acl:relcl">
            <governor idx="6">fire</governor>
            <dependent idx="10">suspicious</dependent>
          </dep>
          <dep type="punct">
            <governor idx="4">says</governor>
            <dependent idx="11">.</dependent>
          </dep>
          <dep type="punct">
            <governor idx="4">says</governor>
            <dependent idx="12">''</dependent>
          </dep>
        </dependencies>
        <dependencies type="collapsed-ccprocessed-dependencies">
          <dep type="root">
            <governor idx="0">ROOT</governor>
            <dependent idx="4">says</dependent>
          </dep>
          <dep type="det">
            <governor idx="3">chief</governor>
            <dependent idx="1">the</dependent>
          </dep>
          <dep type="compound">
            <governor idx="3">chief</governor>
            <dependent idx="2">fire</dependent>
          </dep>
          <dep type="nsubj">
            <governor idx="4">says</governor>
            <dependent idx="3">chief</dependent>
          </dep>
          <dep type="det">
            <governor idx="6">fire</governor>
            <dependent idx="5">the</dependent>
          </dep>
          <dep type="dobj">
            <governor idx="4">says</governor>
            <dependent idx="6">fire</dependent>
          </dep>
          <dep type="punct">
            <governor idx="6">fire</governor>
            <dependent idx="7">''</dependent>
          </dep>
          <dep type="cop">
            <governor idx="10">suspicious</governor>
            <dependent idx="8">is</dependent>
          </dep>
          <dep type="advmod">
            <governor idx="10">suspicious</governor>
            <dependent idx="9">definitely</dependent>
          </dep>
          <dep type="acl:relcl">
            <governor idx="6">fire</governor>
            <dependent idx="10">suspicious</dependent>
          </dep>
          <dep type="punct">
            <governor idx="4">says</governor>
            <dependent idx="11">.</dependent>
          </dep>
          <dep type="punct">
            <governor idx="4">says</governor>
            <dependent idx="12">''</dependent>
          </dep>
        </dependencies>
        <dependencies type="enhanced-dependencies">
          <dep type="root">
            <governor idx="0">ROOT</governor>
            <dependent idx="4">says</dependent>
          </dep>
          <dep type="det">
            <governor idx="3">chief</governor>
            <dependent idx="1">the</dependent>
          </dep>
          <dep type="compound">
            <governor idx="3">chief</governor>
            <dependent idx="2">fire</dependent>
          </dep>
          <dep type="nsubj">
            <governor idx="4">says</governor>
            <dependent idx="3">chief</dependent>
          </dep>
          <dep type="det">
            <governor idx="6">fire</governor>
            <dependent idx="5">the</dependent>
          </dep>
          <dep type="dobj">
            <governor idx="4">says</governor>
            <dependent idx="6">fire</dependent>
          </dep>
          <dep type="punct">
            <governor idx="6">fire</governor>
            <dependent idx="7">''</dependent>
          </dep>
          <dep type="cop">
            <governor idx="10">suspicious</governor>
            <dependent idx="8">is</dependent>
          </dep>
          <dep type="advmod">
            <governor idx="10">suspicious</governor>
            <dependent idx="9">definitely</dependent>
          </dep>
          <dep type="acl:relcl">
            <governor idx="6">fire</governor>
            <dependent idx="10">suspicious</dependent>
          </dep>
          <dep type="punct">
            <governor idx="4">says</governor>
            <dependent idx="11">.</dependent>
          </dep>
          <dep type="punct">
            <governor idx="4">says</governor>
            <dependent idx="12">''</dependent>
          </dep>
        </dependencies>
        <dependencies type="enhanced-plus-plus-dependencies">
          <dep type="root">
            <governor idx="0">ROOT</governor>
            <dependent idx="4">says</dependent>
          </dep>
          <dep type="det">
            <governor idx="3">chief</governor>
            <dependent idx="1">the</dependent>
          </dep>
          <dep type="compound">
            <governor idx="3">chief</governor>
            <dependent idx="2">fire</dependent>
          </dep>
          <dep type="nsubj">
            <governor idx="4">says</governor>
            <dependent idx="3">chief</dependent>
          </dep>
          <dep type="det">
            <governor idx="6">fire</governor>
            <dependent idx="5">the</dependent>
          </dep>
          <dep type="dobj">
            <governor idx="4">says</governor>
            <dependent idx="6">fire</dependent>
          </dep>
          <dep type="punct">
            <governor idx="6">fire</governor>
            <dependent idx="7">''</dependent>
          </dep>
          <dep type="cop">
            <governor idx="10">suspicious</governor>
            <dependent idx="8">is</dependent>
          </dep>
          <dep type="advmod">
            <governor idx="10">suspicious</governor>
            <dependent idx="9">definitely</dependent>
          </dep>
          <dep type="acl:relcl">
            <governor idx="6">fire</governor>
            <dependent idx="10">suspicious</dependent>
          </dep>
          <dep type="punct">
            <governor idx="4">says</governor>
            <dependent idx="11">.</dependent>
          </dep>
          <dep type="punct">
            <governor idx="4">says</governor>
            <dependent idx="12">''</dependent>
          </dep>
        </dependencies>
      </sentence>
      <sentence id="4">
        <tokens>
          <token id="1">
            <word>.</word>
            <lemma>.</lemma>
            <CharacterOffsetBegin>208</CharacterOffsetBegin>
            <CharacterOffsetEnd>209</CharacterOffsetEnd>
            <POS>.</POS>
            <NER>O</NER>
            <Speaker>PER0</Speaker>
          </token>
        </tokens>
        <parse>(ROOT (NP (. .))) </parse>
        <dependencies type="basic-dependencies">
          <dep type="root">
            <governor idx="0">ROOT</governor>
            <dependent idx="1">.</dependent>
          </dep>
        </dependencies>
        <dependencies type="collapsed-dependencies">
          <dep type="root">
            <governor idx="0">ROOT</governor>
            <dependent idx="1">.</dependent>
          </dep>
        </dependencies>
        <dependencies type="collapsed-ccprocessed-dependencies">
          <dep type="root">
            <governor idx="0">ROOT</governor>
            <dependent idx="1">.</dependent>
          </dep>
        </dependencies>
        <dependencies type="enhanced-dependencies">
          <dep type="root">
            <governor idx="0">ROOT</governor>
            <dependent idx="1">.</dependent>
          </dep>
        </dependencies>
        <dependencies type="enhanced-plus-plus-dependencies">
          <dep type="root">
            <governor idx="0">ROOT</governor>
            <dependent idx="1">.</dependent>
          </dep>
        </dependencies>
      </sentence>
      <sentence id="5">
        <tokens>
          <token id="1">
            <word>no</word>
            <lemma>no</lemma>
            <CharacterOffsetBegin>210</CharacterOffsetBegin>
            <CharacterOffsetEnd>212</CharacterOffsetEnd>
            <POS>DT</POS>
            <NER>O</NER>
            <Speaker>PER0</Speaker>
          </token>
          <token id="2">
            <word>one</word>
            <lemma>one</lemma>
            <CharacterOffsetBegin>213</CharacterOffsetBegin>
            <CharacterOffsetEnd>216</CharacterOffsetEnd>
            <POS>NN</POS>
            <NER>NUMBER</NER>
            <NormalizedNER>1.0</NormalizedNER>
            <Speaker>PER0</Speaker>
          </token>
          <token id="3">
            <word>was</word>
            <lemma>be</lemma>
            <CharacterOffsetBegin>217</CharacterOffsetBegin>
            <CharacterOffsetEnd>220</CharacterOffsetEnd>
            <POS>VBD</POS>
            <NER>O</NER>
            <Speaker>PER0</Speaker>
          </token>
          <token id="4">
            <word>hurt</word>
            <lemma>hurt</lemma>
            <CharacterOffsetBegin>221</CharacterOffsetBegin>
            <CharacterOffsetEnd>225</CharacterOffsetEnd>
            <POS>VBN</POS>
            <NER>O</NER>
            <Speaker>PER0</Speaker>
          </token>
          <token id="5">
            <word>.</word>
            <lemma>.</lemma>
            <CharacterOffsetBegin>226</CharacterOffsetBegin>
            <CharacterOffsetEnd>227</CharacterOffsetEnd>
            <POS>.</POS>
            <NER>O</NER>
            <Speaker>PER0</Speaker>
          </token>
        </tokens>
        <parse>(ROOT (S (NP (DT no) (NN one)) (VP (VBD was) (VP (VBN hurt))) (. .))) </parse>
        <dependencies type="basic-dependencies">
          <dep type="root">
            <governor idx="0">ROOT</governor>
            <dependent idx="4">hurt</dependent>
          </dep>
          <dep type="neg">
            <governor idx="2">one</governor>
            <dependent idx="1">no</dependent>
          </dep>
          <dep type="nsubjpass">
            <governor idx="4">hurt</governor>
            <dependent idx="2">one</dependent>
          </dep>
          <dep type="auxpass">
            <governor idx="4">hurt</governor>
            <dependent idx="3">was</dependent>
          </dep>
          <dep type="punct">
            <governor idx="4">hurt</governor>
            <dependent idx="5">.</dependent>
          </dep>
        </dependencies>
        <dependencies type="collapsed-dependencies">
          <dep type="root">
            <governor idx="0">ROOT</governor>
            <dependent idx="4">hurt</dependent>
          </dep>
          <dep type="neg">
            <governor idx="2">one</governor>
            <dependent idx="1">no</dependent>
          </dep>
          <dep type="nsubjpass">
            <governor idx="4">hurt</governor>
            <dependent idx="2">one</dependent>
          </dep>
          <dep type="auxpass">
            <governor idx="4">hurt</governor>
            <dependent idx="3">was</dependent>
          </dep>
          <dep type="punct">
            <governor idx="4">hurt</governor>
            <dependent idx="5">.</dependent>
          </dep>
        </dependencies>
        <dependencies type="collapsed-ccprocessed-dependencies">
          <dep type="root">
            <governor idx="0">ROOT</governor>
            <dependent idx="4">hurt</dependent>
          </dep>
          <dep type="neg">
            <governor idx="2">one</governor>
            <dependent idx="1">no</dependent>
          </dep>
          <dep type="nsubjpass">
            <governor idx="4">hurt</governor>
            <dependent idx="2">one</dependent>
          </dep>
          <dep type="auxpass">
            <governor idx="4">hurt</governor>
            <dependent idx="3">was</dependent>
          </dep>
          <dep type="punct">
            <governor idx="4">hurt</governor>
            <dependent idx="5">.</dependent>
          </dep>
        </dependencies>
        <dependencies type="enhanced-dependencies">
          <dep type="root">
            <governor idx="0">ROOT</governor>
            <dependent idx="4">hurt</dependent>
          </dep>
          <dep type="neg">
            <governor idx="2">one</governor>
            <dependent idx="1">no</dependent>
          </dep>
          <dep type="nsubjpass">
            <governor idx="4">hurt</governor>
            <dependent idx="2">one</dependent>
          </dep>
          <dep type="auxpass">
            <governor idx="4">hurt</governor>
            <dependent idx="3">was</dependent>
          </dep>
          <dep type="punct">
            <governor idx="4">hurt</governor>
            <dependent idx="5">.</dependent>
          </dep>
        </dependencies>
        <dependencies type="enhanced-plus-plus-dependencies">
          <dep type="root">
            <governor idx="0">ROOT</governor>
            <dependent idx="4">hurt</dependent>
          </dep>
          <dep type="neg">
            <governor idx="2">one</governor>
            <dependent idx="1">no</dependent>
          </dep>
          <dep type="nsubjpass">
            <governor idx="4">hurt</governor>
            <dependent idx="2">one</dependent>
          </dep>
          <dep type="auxpass">
            <governor idx="4">hurt</governor>
            <dependent idx="3">was</dependent>
          </dep>
          <dep type="punct">
            <governor idx="4">hurt</governor>
            <dependent idx="5">.</dependent>
          </dep>
        </dependencies>
      </sentence>
    </sentences>
    <coreference/>
  </document>
</root>
